wanglaoshi/Analyzer.py
wanglaoshi/Analyzer_Plain.py
wanglaoshi/JupyterEnv.py
wanglaoshi/JupyterFont.py
wanglaoshi/MLDL.py
wanglaoshi/Useful.py
wanglaoshi/VERSIONS.py
wanglaoshi/WebGetter.py
wanglaoshi/__init__.py
wanglaoshi/utils.py
wanglaoshi/static/.DS_Store
wanglaoshi/static/js/analyzer.js
wanglaoshi/templates/analyzer.html
wanglaoshi-0.11.2.dist-info/METADATA
wanglaoshi-0.11.2.dist-info/WHEEL
wanglaoshi-0.11.2.dist-info/top_level.txt
wanglaoshi-0.11.2.dist-info/RECORD
