Metadata-Version: 2.1
Name: wanglaoshi
Version: 0.11.2
Summary: A utility module for DA and ML and DL tasks
Home-page: https://github.com/wanglaoshi/wanglaoshi-pypi
Author: WangLaoShi
Author-email: ginger547@gmail.com
Classifier: Programming Language :: Python :: 3
Classifier: License :: OSI Approved :: MIT License
Classifier: Operating System :: OS Independent
Requires-Python: >=3.8
Requires-Dist: rich
Requires-Dist: requests
Requires-Dist: pandas
Requires-Dist: numpy
Requires-Dist: matplotlib
Requires-Dist: seaborn
Requires-Dist: scipy
Requires-Dist: missingno
Requires-Dist: jinja2
Requires-Dist: tqdm
Requires-Dist: statsmodels
Requires-Dist: scikit-learn
